{
  "dogeEntry": {
    "date": "2021-03-31",
    "close": 66
  },
  "turns": [
    {
      "turn": 0,
      "date": "2021-04-01",
      "close": 77,
      "fgi": 74,
      "pctFromEntry": 17
    },
    {
      "turn": 1,
      "date": "2021-04-04",
      "close": 73,
      "fgi": 74,
      "pctFromEntry": 11
    },
    {
      "turn": 2,
      "date": "2021-04-08",
      "close": 81,
      "fgi": 73,
      "pctFromEntry": 23
    },
    {
      "turn": 3,
      "date": "2021-04-13",
      "close": 121,
      "fgi": 74,
      "pctFromEntry": 83
    },
    {
      "turn": 4,
      "date": "2021-04-16",
      "close": 467,
      "fgi": 78,
      "pctFromEntry": 608
    },
    {
      "turn": 5,
      "date": "2021-04-18",
      "close": 434,
      "fgi": 79,
      "pctFromEntry": 558
    },
    {
      "turn": 6,
      "date": "2021-04-21",
      "close": 388,
      "fgi": 73,
      "pctFromEntry": 488
    },
    {
      "turn": 7,
      "date": "2021-04-24",
      "close": 327,
      "fgi": 37,
      "pctFromEntry": 395
    },
    {
      "turn": 8,
      "date": "2021-04-28",
      "close": 376,
      "fgi": 59,
      "pctFromEntry": 470
    },
    {
      "turn": 9,
      "date": "2021-05-03",
      "close": 539,
      "fgi": 61,
      "pctFromEntry": 717
    }
  ],
  "snl": {
    "d0503": 539,
    "d0508": 774,
    "d0509": 703,
    "d0515": 636,
    "d0531": 381
  },
  "dogeSeries": [
    [
      "2021-03-30",
      65,
      72
    ],
    [
      "2021-03-31",
      66,
      76
    ],
    [
      "2021-04-01",
      77,
      74
    ],
    [
      "2021-04-04",
      73,
      74
    ],
    [
      "2021-04-08",
      81,
      73
    ],
    [
      "2021-04-13",
      121,
      74
    ],
    [
      "2021-04-16",
      467,
      78
    ],
    [
      "2021-04-18",
      434,
      79
    ],
    [
      "2021-04-21",
      388,
      73
    ],
    [
      "2021-04-24",
      327,
      37
    ],
    [
      "2021-04-28",
      376,
      59
    ],
    [
      "2021-05-03",
      539,
      61
    ],
    [
      "2021-05-08",
      774,
      67
    ],
    [
      "2021-05-15",
      636,
      27
    ]
  ],
  "ftxSeries": [
    [
      "2022-11-07",
      2895,
      33
    ],
    [
      "2022-11-08",
      2665,
      31
    ],
    [
      "2022-11-09",
      2292,
      29
    ],
    [
      "2022-11-10",
      2478,
      22
    ],
    [
      "2022-11-11",
      2366,
      25
    ],
    [
      "2022-11-12",
      2338,
      21
    ],
    [
      "2022-11-13",
      2251,
      22
    ],
    [
      "2022-11-14",
      2270,
      24
    ],
    [
      "2022-11-15",
      2300,
      22
    ],
    [
      "2022-11-16",
      2295,
      23
    ],
    [
      "2022-11-17",
      2298,
      20
    ],
    [
      "2022-11-20",
      2279,
      24
    ],
    [
      "2022-11-22",
      2258,
      22
    ]
  ]
}